example/__init__.py
example/baselines.py
example/log_utils.py
example/policies.py
example/reinforce.py
reinforcement/__init__.py
reinforcement/_version.py
reinforcement/np_operations.py
reinforcement/tf_operations.py
reinforcement/trajectories.py
reinforcement/agents/__init__.py
reinforcement/agents/basis.py
reinforcement/agents/td_agent.py
reinforcement/algorithm/__init__.py
reinforcement/algorithm/reinforce.py
reinforcement/models/__init__.py
reinforcement/models/neural_network.py
reinforcement/models/q_model.py
reinforcement/models/q_regression_model.py
reinforcement/policies/__init__.py
reinforcement/policies/e_greedy_policies.py
reinforcement/reward_functions/__init__.py
reinforcement/reward_functions/q_function.py
reinforcement/reward_functions/q_neuronal.py
reinforcement/reward_functions/q_table.py
reinforcement/reward_functions/value_table.py
tests/aux/__init__.py
tests/aux/agents.py
tests/aux/algorithms.py
tests/aux/baselines.py
tests/aux/common_doubles.py
tests/aux/environments.py
tests/aux/policies.py
tests/aux/q_doubles.py
reinforcement-1.2.0.dist-info/LICENSE
reinforcement-1.2.0.dist-info/METADATA
reinforcement-1.2.0.dist-info/WHEEL
reinforcement-1.2.0.dist-info/top_level.txt
reinforcement-1.2.0.dist-info/RECORD
