Metadata-Version: 2.1
Name: reinforcement
Version: 1.2.0
Summary: A reinforcement learning module
Home-page: https://github.com/SwamyDev/reinforcement
Author: Bernhard Raml
Author-email: pypi-reinforcment@googlegroups.com
License: UNKNOWN
Project-URL: Bug Reports, https://github.com/SwamyDev/reinforcement/issues
Project-URL: Source, https://github.com/SwamyDev/reinforcement/
Keywords: AI reinforcement learning
Platform: UNKNOWN
Classifier: Development Status :: 3 - Alpha
Classifier: Intended Audience :: Developers
Classifier: Topic :: Scientific/Engineering :: Artificial Intelligence
Classifier: License :: OSI Approved :: MIT License
Classifier: Programming Language :: Python :: 3
Provides-Extra: test
Requires-Dist: numpy (<1.17) ; extra == 'test'
Requires-Dist: tensorflow (==1.14) ; extra == 'test'
Requires-Dist: pytest ; extra == 'test'
Requires-Dist: pytest-rerunfailures ; extra == 'test'
Requires-Dist: matplotlib ; extra == 'test'
Requires-Dist: gym ; extra == 'test'
Provides-Extra: tf_cpu
Requires-Dist: numpy (<1.17) ; extra == 'tf_cpu'
Requires-Dist: tensorflow (==1.14) ; extra == 'tf_cpu'
Provides-Extra: tf_gpu
Requires-Dist: numpy (<1.17) ; extra == 'tf_gpu'
Requires-Dist: tensorflow-gpu (==1.14) ; extra == 'tf_gpu'
